LICENSE
MANIFEST.in
README.md
pyproject.toml
src/_core/common.c
src/_core/markdown.c
src/_core/qstrip.h
src/qstrip/__init__.py
src/qstrip/__main__.py
src/qstrip.egg-info/PKG-INFO
src/qstrip.egg-info/SOURCES.txt
src/qstrip.egg-info/dependency_links.txt
src/qstrip.egg-info/entry_points.txt
src/qstrip.egg-info/top_level.txt
tests/test_markdown.py