Metadata-Version: 2.4
Name: qstrip
Version: 0.1.1
Summary: Fast Markdown Stripper
Author-email: Carl von Bonin <contact@carl-vbn.dev>
License-Expression: MIT
Project-URL: Homepage, https://github.com/carl-vbn/qstrip
Requires-Python: >=3.7
License-File: LICENSE
Dynamic: license-file
